simulateur_trafic/__init__.py
simulateur_trafic/main.py
simulateur_trafic/mainGraphique.py
simulateur_trafic/core/__init__.py
simulateur_trafic/core/analyseur.py
simulateur_trafic/core/profiling.py
simulateur_trafic/core/simulateur.py
simulateur_trafic/data/__init__.py
simulateur_trafic/ioo/__init__.py
simulateur_trafic/ioo/affichage.py
simulateur_trafic/ioo/export.py
simulateur_trafic/models/__init__.py
simulateur_trafic/models/reseau.py
simulateur_trafic/models/route.py
simulateur_trafic/models/vehicule.py
simulateur_trafic_mouhebboubaker-0.2.0.dist-info/METADATA
simulateur_trafic_mouhebboubaker-0.2.0.dist-info/WHEEL
simulateur_trafic_mouhebboubaker-0.2.0.dist-info/top_level.txt
simulateur_trafic_mouhebboubaker-0.2.0.dist-info/RECORD
