Metadata-Version: 2.4
Name: simulateur_trafic_MouhebBoubaker
Version: 0.2.0
Summary: Un simulateur de trafic pour modéliser des véhicules sur des routes.
Home-page: https://github.com/mouhebboubaker/simulateur_trafic
Author: Mouheb Boubaker
Author-email: mouhebboubaker2@gmail.com
Classifier: Programming Language :: Python :: 3
Classifier: Programming Language :: Python :: 3.6
Classifier: Programming Language :: Python :: 3.7
Classifier: Programming Language :: Python :: 3.8
Classifier: Programming Language :: Python :: 3.9
Classifier: Programming Language :: Python :: 3.10
Classifier: Programming Language :: Python :: 3.11
Classifier: Programming Language :: Python :: 3.12
Classifier: License :: OSI Approved :: MIT License
Classifier: Operating System :: OS Independent
Classifier: Development Status :: 3 - Alpha
Classifier: Intended Audience :: Developers
Classifier: Topic :: Scientific/Engineering :: Visualization
Requires-Python: >=3.6
Requires-Dist: matplotlib>=3.8.0
Requires-Dist: numpy>=1.26.0
Requires-Dist: pandas>=2.1.0
